dhcpwn.py
dhcpwn-1.1.0.dist-info/METADATA
dhcpwn-1.1.0.dist-info/RECORD
dhcpwn-1.1.0.dist-info/WHEEL
dhcpwn-1.1.0.dist-info/entry_points.txt
dhcpwn-1.1.0.dist-info/top_level.txt
