Metadata-Version: 2.1
Name: dhcpwn
Version: 1.1.0
Summary: All your IPs are belong to us.
Home-page: https://github.com/mschwager/dhcpwn
License: GPLv3
Platform: UNKNOWN
Classifier: Environment :: Console
Classifier: Intended Audience :: Information Technology
Classifier: Intended Audience :: System Administrators
Classifier: License :: OSI Approved :: GNU General Public License v3 (GPLv3)
Classifier: Operating System :: MacOS :: MacOS X
Classifier: Operating System :: Microsoft :: Windows
Classifier: Operating System :: POSIX
Classifier: Programming Language :: Python :: 3.4
Classifier: Programming Language :: Python :: 3.5
Classifier: Programming Language :: Python :: 3.6
Classifier: Topic :: Security
Requires-Python: >=3.0
Requires-Dist: scapy (<3.0.0,>=2.4.0)
